protloc_mex1/AA_count.py
protloc_mex1/GO_count.py
protloc_mex1/IG_calculator.py
protloc_mex1/SHAP_conduct.py
protloc_mex1/SHAP_plus.py
protloc_mex1/__init__.py
protloc_mex1/classifier_evalute.py
protloc_mex1-0.0.24.dist-info/LICENSE.txt
protloc_mex1-0.0.24.dist-info/METADATA
protloc_mex1-0.0.24.dist-info/WHEEL
protloc_mex1-0.0.24.dist-info/top_level.txt
protloc_mex1-0.0.24.dist-info/RECORD
