Metadata-Version: 2.1
Name: protloc_mex1
Version: 0.0.24
Summary: ...
Author-email: Ze Yu Luo <1024226968@qq.com>
Project-URL: Homepage, https://github.com/yujuan-zhang/ProtLoc-mexl
Project-URL: Bug Tracker, https://github.com/yujuan-zhang/ProtLoc-mexl/issues
Classifier: Development Status :: 3 - Alpha
Classifier: Programming Language :: Python :: 3
Classifier: Programming Language :: Python :: 3.9
Classifier: License :: OSI Approved :: MIT License
Classifier: Operating System :: OS Independent
Requires-Python: ==3.9
License-File: LICENSE.txt
Requires-Dist: biopython ==1.79
Requires-Dist: numpy ==1.20.3
Requires-Dist: pandas ==1.4.1
Requires-Dist: seaborn ==0.11.2
Requires-Dist: matplotlib ==3.5.1
Requires-Dist: shap ==0.41.0
Requires-Dist: gensim ==4.2.0
